CompCamps_Cash_Api-1.0.0.dist-info/METADATA
CompCamps_Cash_Api-1.0.0.dist-info/RECORD
CompCamps_Cash_Api-1.0.0.dist-info/WHEEL
CompCamps_Cash_Api-1.0.0.dist-info/top_level.txt
compcamps_cash_api/__init__.py
compcamps_cash_api/entities/__init__.py
compcamps_cash_api/entities/block.py
compcamps_cash_api/entities/keys.py
compcamps_cash_api/entities/prefix.py
compcamps_cash_api/entities/transaction.py
